rchain/__init__.py
rchain/__main__.py
rchain/certificate.py
rchain/client.py
rchain/const.py
rchain/crypto.py
rchain/data_types.py
rchain/interface.py
rchain/meta.py
rchain/param.py
rchain/report.py
rchain/util.py
rchain/vault.py
rchain/pb/CasperMessage_pb2.py
rchain/pb/CasperMessage_pb2.pyi
rchain/pb/CasperMessage_pb2_grpc.py
rchain/pb/DeployServiceCommon_pb2.py
rchain/pb/DeployServiceCommon_pb2.pyi
rchain/pb/DeployServiceCommon_pb2_grpc.py
rchain/pb/DeployServiceV1_pb2.py
rchain/pb/DeployServiceV1_pb2.pyi
rchain/pb/DeployServiceV1_pb2_grpc.py
rchain/pb/ProposeServiceCommon_pb2.py
rchain/pb/ProposeServiceCommon_pb2.pyi
rchain/pb/ProposeServiceCommon_pb2_grpc.py
rchain/pb/ProposeServiceV1_pb2.py
rchain/pb/ProposeServiceV1_pb2.pyi
rchain/pb/ProposeServiceV1_pb2_grpc.py
rchain/pb/RhoTypes_pb2.py
rchain/pb/RhoTypes_pb2.pyi
rchain/pb/RhoTypes_pb2_grpc.py
rchain/pb/ServiceError_pb2.py
rchain/pb/ServiceError_pb2.pyi
rchain/pb/ServiceError_pb2_grpc.py
rchain/pb/__init__.py
rchain/pb/routing_pb2.py
rchain/pb/routing_pb2.pyi
rchain/pb/routing_pb2_grpc.py
rchain/pb/scalapb/__init__.py
rchain/pb/scalapb/scalapb_pb2.py
rchain/pb/scalapb/scalapb_pb2.pyi
rchain/pb/scalapb/scalapb_pb2_grpc.py
rchain/tests/__init__.py
rchain/tests/test_certificate.py
rchain/tests/test_cli.py
rchain/tests/test_client.py
rchain/tests/test_crypto.py
rchain/tests/test_from_pb.py
pyrchain-0.3.12.dist-info/LICENSE
pyrchain-0.3.12.dist-info/METADATA
pyrchain-0.3.12.dist-info/WHEEL
pyrchain-0.3.12.dist-info/entry_points.txt
pyrchain-0.3.12.dist-info/top_level.txt
pyrchain-0.3.12.dist-info/RECORD
