Metadata-Version: 2.1
Name: pyrchain
Version: 0.3.12
Summary: Interface to RChain RNode RPC
Home-page: https://github.com/rchain/pyrchain
Author: RChain Cooperative
Author-email: rchain-makers@rchain.coop
License: UNKNOWN
Platform: UNKNOWN
License-File: LICENSE
Requires-Dist: grpcio
Requires-Dist: protobuf
Requires-Dist: ecdsa
Requires-Dist: python-bitcoinlib
Requires-Dist: cryptography
Requires-Dist: eth-hash
Requires-Dist: pycryptodome
Requires-Dist: eth-keyfile
Requires-Dist: dataclasses
Requires-Dist: click
Provides-Extra: dev
Requires-Dist: grpcio-tools ; extra == 'dev'
Requires-Dist: mypy ; extra == 'dev'
Requires-Dist: typing-extensions ; extra == 'dev'
Requires-Dist: mypy-protobuf ; extra == 'dev'
Requires-Dist: isort ; extra == 'dev'
Requires-Dist: pytest (==4.6.9) ; extra == 'dev'
Requires-Dist: sphinx ; extra == 'dev'
